{
  "checksum": "88a73b17fe8bba9cd9e41fad73cfe61223c3cc3d4f35e20812e27d2250f6adf2",
  "cohort_seed": null,
  "default": {
    "dark": null,
    "light": [
      {
        "cluster_key": "cluster-dashboard",
        "constraint_key": "",
        "metadata": null,
        "properties": null,
        "response_data": {},
        "weight": 1
      }
    ],
    "tap": null
  },
  "name": "dashboard",
  "properties": null,
  "response_data": {},
  "retry_policy": null,
  "rules": null,
  "shared_rules_key": "shared-rules-dashboard",
  "zone_key": "zone-default-zone"
}